main.py
mseep_crypto_feargreed_mcp-0.1.4.dist-info/licenses/LICENSE
mseep_crypto_feargreed_mcp-0.1.4.dist-info/METADATA
mseep_crypto_feargreed_mcp-0.1.4.dist-info/WHEEL
mseep_crypto_feargreed_mcp-0.1.4.dist-info/entry_points.txt
mseep_crypto_feargreed_mcp-0.1.4.dist-info/top_level.txt
mseep_crypto_feargreed_mcp-0.1.4.dist-info/RECORD
