Metadata-Version: 2.4
Name: mseep-crypto-feargreed-mcp
Version: 0.1.4
Summary: Providing real-time and historical Crypto Fear & Greed Index data
Author-email: mseep <support@skydeck.ai>
Requires-Python: >=3.13
License-File: LICENSE
Requires-Dist: httpx>=0.28.1
Requires-Dist: mcp[cli]>=1.4.1
Dynamic: license-file
